AUTHORS.rst
CONTRIBUTING.rst
HISTORY.rst
LICENSE
MANIFEST.in
README.rst
setup.cfg
setup.py
docs/Makefile
docs/authors.rst
docs/conf.py
docs/contributing.rst
docs/history.rst
docs/index.rst
docs/installation.rst
docs/make.bat
docs/readme.rst
docs/usage.rst
repaper/__init__.py
repaper/cli.py
repaper/repaper.py
repaper.egg-info/PKG-INFO
repaper.egg-info/SOURCES.txt
repaper.egg-info/dependency_links.txt
repaper.egg-info/entry_points.txt
repaper.egg-info/not-zip-safe
repaper.egg-info/requires.txt
repaper.egg-info/top_level.txt
repaper/utils/__init__.py
repaper/utils/form_utils.py
tests/__init__.py
tests/test_repaper.py