Metadata-Version: 1.2
Name: repaper
Version: 0.1.2
Summary: Convert form based PDF documents to web based froms or editable pdf forms. 
Home-page: https://github.com/pvbhanuteja/repaper
Author: Bhanu Pallakonda
Author-email: pvbhanuteja@gmail.com
License: MIT license
Keywords: repaper
Platform: UNKNOWN
Classifier: Development Status :: 2 - Pre-Alpha
Classifier: Intended Audience :: Developers
Classifier: License :: OSI Approved :: MIT License
Classifier: Natural Language :: English
Classifier: Programming Language :: Python :: 3
Classifier: Programming Language :: Python :: 3.6
Classifier: Programming Language :: Python :: 3.7
Classifier: Programming Language :: Python :: 3.8
Requires-Python: >=3.6
